odoo8_addon_stock_production_lot_multi_company-8.0.1.0.0-py2.7-nspkg.pth
odoo_addons/stock_production_lot_multi_company/__openerp__.py
odoo_addons/stock_production_lot_multi_company/__init__.py
odoo_addons/stock_production_lot_multi_company/README.rst
odoo_addons/stock_production_lot_multi_company/security/stock_production_lot_security.xml
odoo_addons/stock_production_lot_multi_company/models/stock_production_lot.py
odoo_addons/stock_production_lot_multi_company/models/__init__.py
odoo_addons/stock_production_lot_multi_company/i18n/stock_production_lot_multi_company.pot
odoo_addons/stock_production_lot_multi_company/i18n/es.po
odoo_addons/stock_production_lot_multi_company/views/stock_production_lot_view.xml
odoo_addons/stock_production_lot_multi_company/tests/test_stock_production_lot_multi_company.py
odoo_addons/stock_production_lot_multi_company/tests/__init__.py
odoo8_addon_stock_production_lot_multi_company-8.0.1.0.0.dist-info/top_level.txt
odoo8_addon_stock_production_lot_multi_company-8.0.1.0.0.dist-info/WHEEL
odoo8_addon_stock_production_lot_multi_company-8.0.1.0.0.dist-info/RECORD
odoo8_addon_stock_production_lot_multi_company-8.0.1.0.0.dist-info/metadata.json
odoo8_addon_stock_production_lot_multi_company-8.0.1.0.0.dist-info/DESCRIPTION.rst
odoo8_addon_stock_production_lot_multi_company-8.0.1.0.0.dist-info/METADATA
odoo8_addon_stock_production_lot_multi_company-8.0.1.0.0.dist-info/namespace_packages.txt
